[
  {
    "message": "updated readme to be more specific on how to run this application.",
    "author": {
      "name": "Milind Shah",
      "email": "personalmilind@gmail.com",
      "date": "2017-08-30T21:41:00Z"
    },
    "url": "https://github.com/promilo/Chatty/commit/a8f15831ccde05a67b6864fe3f5129ea9941a088",
    "sha": "a8f15831ccde05a67b6864fe3f5129ea9941a088"
  },
  {
    "message": "Finished randomizing colorss for every user",
    "author": {
      "name": "promilo",
      "email": "milind.shah@mail.utoronto.ca",
      "date": "2017-07-15T22:52:53Z"
    },
    "url": "https://github.com/promilo/Chatty/commit/96cc00bc701f62fc1e4d487b1ac8a4ff15d3b2ed",
    "sha": "96cc00bc701f62fc1e4d487b1ac8a4ff15d3b2ed"
  },
  {
    "message": "Fixed the message list component",
    "author": {
      "name": "promilo",
      "email": "milind.shah@mail.utoronto.ca",
      "date": "2017-07-14T23:50:16Z"
    },
    "url": "https://github.com/promilo/Chatty/commit/4dd52fd785f39102c6284d03cd92948c2ec759cf",
    "sha": "4dd52fd785f39102c6284d03cd92948c2ec759cf"
  },
  {
    "message": "Added package.json file for dependendencies",
    "author": {
      "name": "promilo",
      "email": "milind.shah@mail.utoronto.ca",
      "date": "2017-06-05T00:42:57Z"
    },
    "url": "https://github.com/promilo/Chatty/commit/9d37cc13e8caec3cbfa0f729a6acef7794d86cf1",
    "sha": "9d37cc13e8caec3cbfa0f729a6acef7794d86cf1"
  },
  {
    "message": "Edited the readme file",
    "author": {
      "name": "promilo",
      "email": "milind.shah@mail.utoronto.ca",
      "date": "2017-06-04T16:23:35Z"
    },
    "url": "https://github.com/promilo/Chatty/commit/3c891772aaddd1318593fcf1f314b0cc1ac28f3f",
    "sha": "3c891772aaddd1318593fcf1f314b0cc1ac28f3f"
  },
  {
    "message": "updated the read me",
    "author": {
      "name": "promilo",
      "email": "milind.shah@mail.utoronto.ca",
      "date": "2017-06-04T16:21:34Z"
    },
    "url": "https://github.com/promilo/Chatty/commit/009004bd6691051123a57bff0c2408cf516f16c2",
    "sha": "009004bd6691051123a57bff0c2408cf516f16c2"
  },
  {
    "message": "Added some changes to display online users and change the username",
    "author": {
      "name": "promilo",
      "email": "milind.shah@mail.utoronto.ca",
      "date": "2017-06-04T16:12:32Z"
    },
    "url": "https://github.com/promilo/Chatty/commit/ea1bc32c3745c72e69b01001335e1f844124ba45",
    "sha": "ea1bc32c3745c72e69b01001335e1f844124ba45"
  },
  {
    "message": "Finished implementing hte number of users functinoality",
    "author": {
      "name": "promilo",
      "email": "milind.shah@mail.utoronto.ca",
      "date": "2017-06-02T18:53:05Z"
    },
    "url": "https://github.com/promilo/Chatty/commit/d26777c4110a02c11f668a53a7a4c29df73d896f",
    "sha": "d26777c4110a02c11f668a53a7a4c29df73d896f"
  },
  {
    "message": "fixed bug",
    "author": {
      "name": "promilo",
      "email": "milind.shah@mail.utoronto.ca",
      "date": "2017-06-01T21:45:27Z"
    },
    "url": "https://github.com/promilo/Chatty/commit/e2c279493f07928214887dd29332bddf4d3bba64",
    "sha": "e2c279493f07928214887dd29332bddf4d3bba64"
  },
  {
    "message": "fixed a bug to broadcast to all clients",
    "author": {
      "name": "promilo",
      "email": "milind.shah@mail.utoronto.ca",
      "date": "2017-06-01T20:03:25Z"
    },
    "url": "https://github.com/promilo/Chatty/commit/03f9b9080998dbdd58da0a5da7dcbda332a0cadd",
    "sha": "03f9b9080998dbdd58da0a5da7dcbda332a0cadd"
  },
  {
    "message": "able to broadcast to all clients that the user name has been changed",
    "author": {
      "name": "promilo",
      "email": "milind.shah@mail.utoronto.ca",
      "date": "2017-06-01T19:52:01Z"
    },
    "url": "https://github.com/promilo/Chatty/commit/796b45dd579248e9ddf4eec1e9e43b49d7084515",
    "sha": "796b45dd579248e9ddf4eec1e9e43b49d7084515"
  },
  {
    "message": "Modified the app so that this.state.currentUser is updated",
    "author": {
      "name": "promilo",
      "email": "milind.shah@mail.utoronto.ca",
      "date": "2017-06-01T18:22:14Z"
    },
    "url": "https://github.com/promilo/Chatty/commit/eccfe94bff1b632662365ebb05fb845d7f85dfcb",
    "sha": "eccfe94bff1b632662365ebb05fb845d7f85dfcb"
  },
  {
    "message": "Added realtime chat functionality",
    "author": {
      "name": "promilo",
      "email": "milind.shah@mail.utoronto.ca",
      "date": "2017-05-31T23:20:10Z"
    },
    "url": "https://github.com/promilo/Chatty/commit/7ba827807b84507f3c2dba072e7d1193d9c730c8",
    "sha": "7ba827807b84507f3c2dba072e7d1193d9c730c8"
  },
  {
    "message": "Successfully made a connection to send data to the server",
    "author": {
      "name": "promilo",
      "email": "milind.shah@mail.utoronto.ca",
      "date": "2017-05-31T19:12:54Z"
    },
    "url": "https://github.com/promilo/Chatty/commit/089425fb5c84c00f72e99b78573a3b82457245ae",
    "sha": "089425fb5c84c00f72e99b78573a3b82457245ae"
  },
  {
    "message": "Made a connection to the server",
    "author": {
      "name": "promilo",
      "email": "milind.shah@mail.utoronto.ca",
      "date": "2017-05-31T18:34:18Z"
    },
    "url": "https://github.com/promilo/Chatty/commit/d3e5fbb1191d38e3f8b3f68f99d7754a5973dab2",
    "sha": "d3e5fbb1191d38e3f8b3f68f99d7754a5973dab2"
  },
  {
    "message": "Fixed the rendering username and content form bars",
    "author": {
      "name": "promilo",
      "email": "milind.shah@mail.utoronto.ca",
      "date": "2017-05-31T17:56:11Z"
    },
    "url": "https://github.com/promilo/Chatty/commit/b05e62984a601f50c42847df704d09cec98be926",
    "sha": "b05e62984a601f50c42847df704d09cec98be926"
  },
  {
    "message": "Finished entering new message to the message list",
    "author": {
      "name": "promilo",
      "email": "milind.shah@mail.utoronto.ca",
      "date": "2017-05-31T17:52:11Z"
    },
    "url": "https://github.com/promilo/Chatty/commit/b715bee477ed7cb2ac14ed6d4ab462a3276a41a2",
    "sha": "b715bee477ed7cb2ac14ed6d4ab462a3276a41a2"
  },
  {
    "message": "Able to print every message",
    "author": {
      "name": "promilo",
      "email": "milind.shah@mail.utoronto.ca",
      "date": "2017-05-30T20:49:17Z"
    },
    "url": "https://github.com/promilo/Chatty/commit/de2832962e0b533b90ab4e8e0c353c64597899f2",
    "sha": "de2832962e0b533b90ab4e8e0c353c64597899f2"
  },
  {
    "message": "Splitted up the components",
    "author": {
      "name": "promilo",
      "email": "milind.shah@mail.utoronto.ca",
      "date": "2017-05-30T19:42:33Z"
    },
    "url": "https://github.com/promilo/Chatty/commit/67a8d606900b8825bb63bbbe58f094da69d421a4",
    "sha": "67a8d606900b8825bb63bbbe58f094da69d421a4"
  },
  {
    "message": "Merge pull request #6 from daegren/master\n\nUpdate lint script to scan JSX files",
    "author": {
      "name": "hora",
      "email": "hora@users.noreply.github.com",
      "date": "2017-05-23T04:33:44Z"
    },
    "url": "https://github.com/promilo/Chatty/commit/2227649a3c62514f84842d9e31c969ebda275f6b",
    "sha": "2227649a3c62514f84842d9e31c969ebda275f6b"
  },
  {
    "message": "Merge pull request #5 from vaz/watch-ignore-node-modules\n\n[High CPU/slowdowns issue] webpack watch should ignore node_modules",
    "author": {
      "name": "hora",
      "email": "hora@users.noreply.github.com",
      "date": "2017-05-23T04:33:02Z"
    },
    "url": "https://github.com/promilo/Chatty/commit/dd418d54706acffeed2d68d75520078d9fb9c3c5",
    "sha": "dd418d54706acffeed2d68d75520078d9fb9c3c5"
  },
  {
    "message": "Merge pull request #3 from davidvandusen/feature/webpack-2\n\nUpdate dependencies, migrate to webpack v2",
    "author": {
      "name": "hora",
      "email": "hora@users.noreply.github.com",
      "date": "2017-05-23T04:32:38Z"
    },
    "url": "https://github.com/promilo/Chatty/commit/9499c8aaa6a420a7d8169aa91561f8b1b0aa8188",
    "sha": "9499c8aaa6a420a7d8169aa91561f8b1b0aa8188"
  },
  {
    "message": "Merge pull request #2 from lighthouse-labs/update-readme-instructions\n\nAdded instruction to cd into the cloned directory before removing remotes",
    "author": {
      "name": "hora",
      "email": "hora@users.noreply.github.com",
      "date": "2017-05-23T04:32:17Z"
    },
    "url": "https://github.com/promilo/Chatty/commit/294b13c0ca9417a46b2ffd453e3f5b02965ff175",
    "sha": "294b13c0ca9417a46b2ffd453e3f5b02965ff175"
  },
  {
    "message": "Update lint script to scan JSX files",
    "author": {
      "name": "David Mills",
      "email": "dave@1morepx.com",
      "date": "2017-05-10T19:12:45Z"
    },
    "url": "https://github.com/promilo/Chatty/commit/07b7821c5fdcb8f0a7752546785bde47fd9ea4d1",
    "sha": "07b7821c5fdcb8f0a7752546785bde47fd9ea4d1"
  },
  {
    "message": "webpack watch should ignore node_modules\n\nThis is quite likely to be the cause of the common high CPU\nusage and excessive slowdown experienced by students using\nthis boilerplate.\n\nThis only happens because we turn on polling, but we turn\non polling because we have to (for Vagrant).\n\nSee https://github.com/webpack/watchpack/pull/23",
    "author": {
      "name": "vaz",
      "email": "v@tryptid.com",
      "date": "2017-04-04T02:43:14Z"
    },
    "url": "https://github.com/promilo/Chatty/commit/c26ba3203cdeefa3d5c349b2a93f662f60aac066",
    "sha": "c26ba3203cdeefa3d5c349b2a93f662f60aac066"
  },
  {
    "message": "Migrate webpack.config.js to webpack 2\n\nFollowing instructions in https://webpack.js.org/guides/migrating/",
    "author": {
      "name": "David VanDusen",
      "email": "github@davidvandusen.com",
      "date": "2017-02-15T21:45:44Z"
    },
    "url": "https://github.com/promilo/Chatty/commit/62c08975001757d364dabde919668150de05109b",
    "sha": "62c08975001757d364dabde919668150de05109b"
  },
  {
    "message": "Update dependencies to latest",
    "author": {
      "name": "David VanDusen",
      "email": "github@davidvandusen.com",
      "date": "2017-02-15T21:36:05Z"
    },
    "url": "https://github.com/promilo/Chatty/commit/d3b5cf903b56f814f64582f553e7be1bee66010e",
    "sha": "d3b5cf903b56f814f64582f553e7be1bee66010e"
  },
  {
    "message": "adds instruction to cd before rm-ing remotes",
    "author": {
      "name": "Horatiu Halmaghi",
      "email": "hhalmaghi@gmail.com",
      "date": "2017-02-06T18:24:44Z"
    },
    "url": "https://github.com/promilo/Chatty/commit/4514f47a3958966d417d44cabb05c63207eef72a",
    "sha": "4514f47a3958966d417d44cabb05c63207eef72a"
  },
  {
    "message": "Merge pull request #1 from fzero/fix-vagrant-hmr\n\nAdded `watchOptions` to fix automatic rebuild on Vagrant",
    "author": {
      "name": "Khurram Virani",
      "email": "kvirani@gmail.com",
      "date": "2016-10-03T17:51:36Z"
    },
    "url": "https://github.com/promilo/Chatty/commit/b73edf6a3017f078439b0b4a1765627fddc44fd3",
    "sha": "b73edf6a3017f078439b0b4a1765627fddc44fd3"
  },
  {
    "message": "Require node >= 6",
    "author": {
      "name": "Monica Olinescu",
      "email": "monica.olinescu@gmail.com",
      "date": "2016-09-02T23:23:16Z"
    },
    "url": "https://github.com/promilo/Chatty/commit/95824070497cb4f545d6e1669a1f4dbac930f29b",
    "sha": "95824070497cb4f545d6e1669a1f4dbac930f29b"
  }
]